{
  "preRequisites:9": {
    "0:10": {
      "questIDHigh:4": 5030960030020157572,
      "questIDLow:4": -7575966463346839542
    }
  },
  "properties:10": {
    "betterquesting:10": {
      "autoClaim:1": 0,
      "desc:8": "你研究很长时间，终于造出了外星科技的控制中枢，多么神奇的科技！只要通电水晶就会散发出彩色光芒，你相信他不只是一个彩色灯泡这么简单。",
      "globalShare:1": 0,
      "icon:10": {
        "Count:3": 1,
        "Damage:2": 0,
        "OreDict:8": "",
        "id:8": "appliedenergistics2:tile.BlockController"
      },
      "isMain:1": 0,
      "isSilent:1": 0,
      "lockedProgress:1": 0,
      "name:8": "迷人的科技",
      "questLogic:8": "AND",
      "repeatTime:3": -1,
      "repeat_relative:1": 1,
      "simultaneous:1": 0,
      "snd_complete:8": "random.levelup",
      "snd_update:8": "random.levelup",
      "taskLogic:8": "AND",
      "visibility:8": "NORMAL"
    }
  },
  "questIDHigh:4": 1332696685118179360,
  "questIDLow:4": -5122879729510569443,
  "rewards:9": {
    "0:10": {
      "ignoreDisabled:1": 0,
      "index:3": 0,
      "rewardID:8": "bq_standard:item",
      "rewards:9": {
        "0:10": {
          "Count:3": 12,
          "Damage:2": 56,
          "OreDict:8": "",
          "id:8": "appliedenergistics2:item.ItemMultiPart"
        },
        "1:10": {
          "Count:3": 6,
          "Damage:2": 44,
          "OreDict:8": "",
          "id:8": "appliedenergistics2:item.ItemMultiMaterial"
        },
        "2:10": {
          "Count:3": 6,
          "Damage:2": 43,
          "OreDict:8": "",
          "id:8": "appliedenergistics2:item.ItemMultiMaterial"
        }
      }
    }
  },
  "tasks:9": {
    "0:10": {
      "allowAnvil:1": 0,
      "allowCraft:1": 1,
      "allowCraftedFromStatistics:1": 0,
      "allowSmelt:1": 1,
      "ignoreNBT:1": 1,
      "index:3": 0,
      "partialMatch:1": 1,
      "requiredItems:9": {
        "0:10": {
          "Count:3": 1,
          "Damage:2": 0,
          "OreDict:8": "",
          "id:8": "appliedenergistics2:tile.BlockController"
        }
      },
      "taskID:8": "bq_standard:crafting"
    }
  }
}