{
  "preRequisites:9": {
    "0:10": {
      "questIDHigh:4": -3110708570580955685,
      "questIDLow:4": -7396923419749970144
    }
  },
  "properties:10": {
    "betterquesting:10": {
      "autoClaim:1": 0,
      "desc:8": "在尝试使用这种奇特的植物之后，你发现这种植物可能是你在荒凉水星生存的关键，使用更高级的精华来升级你的入魔石！",
      "globalShare:1": 0,
      "icon:10": {
        "Count:3": 1,
        "Damage:2": 0,
        "OreDict:8": "",
        "id:8": "magicalcrops:InfusionStoneRegular"
      },
      "isMain:1": 0,
      "isSilent:1": 0,
      "lockedProgress:1": 0,
      "name:8": "基础之物",
      "questLogic:8": "AND",
      "repeatTime:3": -1,
      "repeat_relative:1": 1,
      "simultaneous:1": 0,
      "snd_complete:8": "random.levelup",
      "snd_update:8": "random.levelup",
      "taskLogic:8": "AND",
      "visibility:8": "NORMAL"
    }
  },
  "questIDHigh:4": 8901325596787625796,
  "questIDLow:4": -6186031781163221080,
  "rewards:9": {
    "0:10": {
      "ignoreDisabled:1": 0,
      "index:3": 0,
      "rewardID:8": "bq_standard:item",
      "rewards:9": {
        "0:10": {
          "Count:3": 8,
          "Damage:2": 0,
          "OreDict:8": "",
          "id:8": "magicalcrops:MagicalFertilizer"
        },
        "1:10": {
          "Count:3": 1,
          "Damage:2": 0,
          "OreDict:8": "",
          "id:8": "magicalcrops:CropBooster"
        }
      }
    }
  },
  "tasks:9": {
    "0:10": {
      "autoConsume:1": 0,
      "consume:1": 0,
      "groupDetect:1": 0,
      "ignoreNBT:1": 1,
      "index:3": 0,
      "partialMatch:1": 1,
      "requiredItems:9": {
        "0:10": {
          "Count:3": 1,
          "Damage:2": 0,
          "OreDict:8": "",
          "id:8": "magicalcrops:InfusionStoneRegular"
        }
      },
      "taskID:8": "bq_standard:retrieval"
    }
  }
}